bingy/__init__.py
bingy/aio/__init__.py
bingy-0.1.0.dist-info/METADATA
bingy-0.1.0.dist-info/WHEEL
bingy-0.1.0.dist-info/top_level.txt
bingy-0.1.0.dist-info/RECORD
