Metadata-Version: 2.1
Name: bingy
Version: 0.1.0
Summary: A simple module for searching on DuckDuckGo
Home-page: https://github.com/AmanoTeam/bingpy
Author: Amano Team
Author-email: contact@amanoteam.com
License: MIT
Platform: UNKNOWN
Requires-Dist: bs4
Requires-Dist: urllib3
Requires-Dist: aiohttp
Requires-Dist: certifi
